qr_stego/__init__.py
qr_stego/__main__.py
qr_stego/data/decoy_templates.yaml
qr_stego_secure-1.0.6.dist-info/licenses/LICENSE
qr_stego_secure-1.0.6.dist-info/METADATA
qr_stego_secure-1.0.6.dist-info/WHEEL
qr_stego_secure-1.0.6.dist-info/entry_points.txt
qr_stego_secure-1.0.6.dist-info/top_level.txt
qr_stego_secure-1.0.6.dist-info/RECORD
