Metadata-Version: 2.4
Name: qr-stego-secure
Version: 1.0.6
Summary: Secure QR Steganography and Encryption Tool
Author: Vishnu
Classifier: Programming Language :: Python :: 3
Classifier: License :: OSI Approved :: MIT License
Classifier: Operating System :: OS Independent
Classifier: Intended Audience :: Developers
Requires-Python: >=3.7
License-File: LICENSE
Requires-Dist: cryptography>=42.0.0
Requires-Dist: Pillow>=10.0.0
Requires-Dist: qrcode[pil]>=7.4.2
Dynamic: author
Dynamic: classifier
Dynamic: description
Dynamic: description-content-type
Dynamic: license-file
Dynamic: requires-dist
Dynamic: requires-python
Dynamic: summary
